odoo9_addon_res_partner_attributes_add_NEQ-9.0.1.0.0-py2.7-nspkg.pth
odoo_addons/res_partner_attributes_add_NEQ/__openerp__.py
odoo_addons/res_partner_attributes_add_NEQ/__init__.py
odoo_addons/res_partner_attributes_add_NEQ/README.rst
odoo_addons/res_partner_attributes_add_NEQ/models/res_partner.py
odoo_addons/res_partner_attributes_add_NEQ/models/__init__.py
odoo_addons/res_partner_attributes_add_NEQ/i18n/nb_NO.po
odoo_addons/res_partner_attributes_add_NEQ/i18n/fr_CA.po
odoo_addons/res_partner_attributes_add_NEQ/i18n/sl.po
odoo_addons/res_partner_attributes_add_NEQ/i18n/fr.po
odoo_addons/res_partner_attributes_add_NEQ/i18n/res_partner_attributes_add_NEQ.pot
odoo_addons/res_partner_attributes_add_NEQ/views/res_partner.xml
odoo9_addon_res_partner_attributes_add_NEQ-9.0.1.0.0.dist-info/top_level.txt
odoo9_addon_res_partner_attributes_add_NEQ-9.0.1.0.0.dist-info/WHEEL
odoo9_addon_res_partner_attributes_add_NEQ-9.0.1.0.0.dist-info/RECORD
odoo9_addon_res_partner_attributes_add_NEQ-9.0.1.0.0.dist-info/metadata.json
odoo9_addon_res_partner_attributes_add_NEQ-9.0.1.0.0.dist-info/DESCRIPTION.rst
odoo9_addon_res_partner_attributes_add_NEQ-9.0.1.0.0.dist-info/METADATA
odoo9_addon_res_partner_attributes_add_NEQ-9.0.1.0.0.dist-info/namespace_packages.txt
